{
    "0": {
        "Avenue": {
            "INFORMATORY_SIGNS": 1
        },
        "Median": {},
        "Center": {},
        "lat": 19.14356403,
        "lng": 84.70774442,
        "to_lat": 19.1428868,
        "to_lng": 84.70753155
    },
    "85": {
        "Avenue": {},
        "Median": {
            "HAZARD": 1,
            "PROHIBITORY_MANDATORY_SIGNS": 1,
            "CHEVRON": 4
        },
        "Center": {},
        "lat": 19.1428868,
        "lng": 84.70753155,
        "to_lat": 19.13847248,
        "to_lng": 84.70676272
    },
    "585": {
        "Avenue": {
            "CAUTIONARY_WARNING_SIGNS": 1
        },
        "Median": {},
        "Center": {},
        "lat": 19.13847248,
        "lng": 84.70676272,
        "to_lat": 19.13399328,
        "to_lng": 84.70631398
    },
    "1085": {
        "Avenue": {
            "INFORMATORY_SIGNS": 2,
            "HAZARD": 1
        },
        "Median": {},
        "Center": {},
        "lat": 19.13399328,
        "lng": 84.70631398,
        "to_lat": 19.12962147,
        "to_lng": 84.7050991
    },
    "1585": {
        "Avenue": {},
        "Median": {},
        "Center": {},
        "lat": 19.12962147,
        "lng": 84.7050991,
        "to_lat": 19.12533812,
        "to_lng": 84.7037781
    },
    "2085": {
        "Avenue": {},
        "Median": {
            "HAZARD": 1
        },
        "Center": {},
        "lat": 19.12533812,
        "lng": 84.7037781,
        "to_lat": 19.120988,
        "to_lng": 84.70243028
    },
    "2585": {
        "Avenue": {},
        "Median": {},
        "Center": {},
        "lat": 19.120988,
        "lng": 84.70243028,
        "to_lat": 19.11680585,
        "to_lng": 84.70111628
    },
    "3085": {
        "Avenue": {},
        "Median": {
            "PROHIBITORY_MANDATORY_SIGNS": 1,
            "CAUTIONARY_WARNING_SIGNS": 1
        },
        "Center": {},
        "lat": 19.11680585,
        "lng": 84.70111628,
        "to_lat": 19.11233388,
        "to_lng": 84.69973323
    },
    "3585": {
        "Avenue": {
            "INFORMATORY_SIGNS": 1,
            "HAZARD": 1
        },
        "Median": {
            "HAZARD": 1
        },
        "Center": {},
        "lat": 19.11233388,
        "lng": 84.69973323,
        "to_lat": 19.10811507,
        "to_lng": 84.6983654
    },
    "4085": {
        "Avenue": {
            "CHEVRON": 4,
            "HAZARD": 2
        },
        "Median": {
            "HAZARD": 1
        },
        "Center": {},
        "lat": 19.10811507,
        "lng": 84.6983654,
        "to_lat": 19.10384503,
        "to_lng": 84.69661643
    },
    "4585": {
        "Avenue": {
            "CHEVRON": 3,
            "HAZARD": 1
        },
        "Median": {
            "HAZARD": 1
        },
        "Center": {},
        "lat": 19.10384503,
        "lng": 84.69661643,
        "to_lat": 19.10078217,
        "to_lng": 84.6931976
    },
    "5085": {
        "Avenue": {
            "HAZARD": 1
        },
        "Median": {
            "HAZARD": 2
        },
        "Center": {},
        "lat": 19.10078217,
        "lng": 84.6931976,
        "to_lat": 19.09818368,
        "to_lng": 84.68939712
    },
    "5585": {
        "Avenue": {
            "HAZARD": 2,
            "INFORMATORY_SIGNS": 1
        },
        "Median": {
            "CAUTIONARY_WARNING_SIGNS": 2,
            "PROHIBITORY_MANDATORY_SIGNS": 1,
            "HAZARD": 1
        },
        "Center": {},
        "lat": 19.09818368,
        "lng": 84.68939712,
        "to_lat": 19.09616912,
        "to_lng": 84.68518813
    },
    "6085": {
        "Avenue": {
            "HAZARD": 1,
            "PROHIBITORY_MANDATORY_SIGNS": 1
        },
        "Median": {},
        "Center": {},
        "lat": 19.09616912,
        "lng": 84.68518813,
        "to_lat": 19.09415623,
        "to_lng": 84.68088025
    },
    "6585": {
        "Avenue": {
            "HAZARD": 1
        },
        "Median": {
            "CHEVRON": 2
        },
        "Center": {},
        "lat": 19.09415623,
        "lng": 84.68088025,
        "to_lat": 19.0921809,
        "to_lng": 84.67666433
    },
    "7085": {
        "Avenue": {},
        "Median": {
            "CHEVRON": 5
        },
        "Center": {},
        "lat": 19.0921809,
        "lng": 84.67666433,
        "to_lat": 19.0894427,
        "to_lng": 84.6728605
    },
    "7585": {
        "Avenue": {
            "HAZARD": 2
        },
        "Median": {
            "CAUTIONARY_WARNING_SIGNS": 2,
            "HAZARD": 2
        },
        "Center": {},
        "lat": 19.0894427,
        "lng": 84.6728605,
        "to_lat": 19.08559277,
        "to_lng": 84.6704059
    },
    "8085": {
        "Avenue": {},
        "Median": {},
        "Center": {},
        "lat": 19.08559277,
        "lng": 84.6704059,
        "to_lat": 19.08183102,
        "to_lng": 84.66796445
    },
    "8585": {
        "Avenue": {},
        "Median": {
            "CAUTIONARY_WARNING_SIGNS": 1,
            "HAZARD": 1
        },
        "Center": {},
        "lat": 19.08183102,
        "lng": 84.66796445,
        "to_lat": 19.07851995,
        "to_lng": 84.66462592
    },
    "9085": {
        "Avenue": {
            "HAZARD": 1
        },
        "Median": {
            "CAUTIONARY_WARNING_SIGNS": 1,
            "PROHIBITORY_MANDATORY_SIGNS": 1,
            "DAMAGED_SIGN": 1
        },
        "Center": {},
        "lat": 19.07851995,
        "lng": 84.66462592,
        "to_lat": 19.07539482,
        "to_lng": 84.6612572
    },
    "9585": {
        "Avenue": {},
        "Median": {
            "HAZARD": 2
        },
        "Center": {},
        "lat": 19.07539482,
        "lng": 84.6612572,
        "to_lat": 19.07179872,
        "to_lng": 84.65820715
    },
    "10085": {
        "Avenue": {
            "CAUTIONARY_WARNING_SIGNS": 1,
            "INFORMATORY_SIGNS": 2,
            "HAZARD": 1,
            "CHEVRON": 3
        },
        "Median": {
            "CAUTIONARY_WARNING_SIGNS": 2,
            "HAZARD": 1
        },
        "Center": {},
        "lat": 19.07179872,
        "lng": 84.65820715,
        "to_lat": 19.06862193,
        "to_lng": 84.65493018
    },
    "10585": {
        "Avenue": {
            "HAZARD": 2,
            "INFORMATORY_SIGNS": 6
        },
        "Median": {
            "HAZARD": 1,
            "CAUTIONARY_WARNING_SIGNS": 1,
            "INFORMATORY_SIGNS": 1
        },
        "Center": {},
        "lat": 19.06862193,
        "lng": 84.65493018,
        "to_lat": 19.06578092,
        "to_lng": 84.65130027
    },
    "11085": {
        "Avenue": {
            "PROHIBITORY_MANDATORY_SIGNS": 1,
            "HAZARD": 1
        },
        "Median": {
            "HAZARD": 1
        },
        "Center": {},
        "lat": 19.06578092,
        "lng": 84.65130027,
        "to_lat": 19.06288573,
        "to_lng": 84.64764953
    },
    "11585": {
        "Avenue": {},
        "Median": {},
        "Center": {},
        "lat": 19.06288573,
        "lng": 84.64764953,
        "to_lat": 19.05992467,
        "to_lng": 84.64405693
    },
    "12085": {
        "Avenue": {
            "PROHIBITORY_MANDATORY_SIGNS": 1,
            "INFORMATORY_SIGNS": 7
        },
        "Median": {
            "HAZARD": 2,
            "PROHIBITORY_MANDATORY_SIGNS": 1
        },
        "Center": {},
        "lat": 19.05992467,
        "lng": 84.64405693,
        "to_lat": 19.05628015,
        "to_lng": 84.64112823
    },
    "12585": {
        "Avenue": {
            "INFORMATORY_SIGNS": 1,
            "HAZARD": 1
        },
        "Median": {
            "PROHIBITORY_MANDATORY_SIGNS": 1,
            "HAZARD": 1
        },
        "Center": {},
        "lat": 19.05628015,
        "lng": 84.64112823,
        "to_lat": 19.05299972,
        "to_lng": 84.63825795
    },
    "13085": {
        "Avenue": {},
        "Median": {},
        "Center": {},
        "lat": 19.05299972,
        "lng": 84.63825795,
        "to_lat": 19.04945363,
        "to_lng": 84.63527265
    },
    "13585": {
        "Avenue": {
            "INFORMATORY_SIGNS": 1,
            "HAZARD": 1
        },
        "Median": {
            "INFORMATORY_SIGNS": 2
        },
        "Center": {},
        "lat": 19.04945363,
        "lng": 84.63527265,
        "to_lat": 19.04617865,
        "to_lng": 84.63197855
    },
    "14085": {
        "Avenue": {
            "CAUTIONARY_WARNING_SIGNS": 1,
            "DIGITAL_SPEED_DISPLAY_SIGNS": 1
        },
        "Median": {},
        "Center": {},
        "lat": 19.04617865,
        "lng": 84.63197855,
        "to_lat": 19.04299467,
        "to_lng": 84.62862732
    },
    "14585": {
        "Avenue": {
            "INFORMATORY_SIGNS": 1,
            "PROHIBITORY_MANDATORY_SIGNS": 1
        },
        "Median": {},
        "Center": {},
        "lat": 19.04299467,
        "lng": 84.62862732,
        "to_lat": 19.03978123,
        "to_lng": 84.62519938
    },
    "15085": {
        "Avenue": {
            "HAZARD": 2,
            "PROHIBITORY_MANDATORY_SIGNS": 1
        },
        "Median": {
            "CHEVRON": 4
        },
        "Center": {},
        "lat": 19.03978123,
        "lng": 84.62519938,
        "to_lat": 19.0361234,
        "to_lng": 84.6224913
    },
    "15585": {
        "Avenue": {
            "PROHIBITORY_MANDATORY_SIGNS": 1,
            "INFORMATORY_SIGNS": 1,
            "HAZARD": 1
        },
        "Median": {
            "PROHIBITORY_MANDATORY_SIGNS": 1
        },
        "Center": {},
        "lat": 19.0361234,
        "lng": 84.6224913,
        "to_lat": 19.03220247,
        "to_lng": 84.62031227
    },
    "16085": {
        "Avenue": {},
        "Median": {},
        "Center": {},
        "lat": 19.03220247,
        "lng": 84.62031227,
        "to_lat": 19.0285854,
        "to_lng": 84.61742032
    },
    "16585": {
        "Avenue": {
            "HAZARD": 1
        },
        "Median": {
            "HAZARD": 1
        },
        "Center": {},
        "lat": 19.0285854,
        "lng": 84.61742032,
        "to_lat": 19.0252588,
        "to_lng": 84.61415115
    },
    "17085": {
        "Avenue": {
            "CAUTIONARY_WARNING_SIGNS": 2,
            "PROHIBITORY_MANDATORY_SIGNS": 1,
            "HAZARD": 1
        },
        "Median": {
            "CHEVRON": 5,
            "PROHIBITORY_MANDATORY_SIGNS": 1,
            "CAUTIONARY_WARNING_SIGNS": 1
        },
        "Center": {},
        "lat": 19.0252588,
        "lng": 84.61415115,
        "to_lat": 19.02176385,
        "to_lng": 84.6113846
    },
    "17585": {
        "Avenue": {
            "CHEVRON": 4,
            "INFORMATORY_SIGNS": 2,
            "HAZARD": 1
        },
        "Median": {
            "CHEVRON": 1,
            "CAUTIONARY_WARNING_SIGNS": 1,
            "PROHIBITORY_MANDATORY_SIGNS": 1,
            "HAZARD": 1
        },
        "Center": {},
        "lat": 19.02176385,
        "lng": 84.6113846,
        "to_lat": 19.01765948,
        "to_lng": 84.60945745
    },
    "18085": {
        "Avenue": {
            "CHEVRON": 1,
            "CAUTIONARY_WARNING_SIGNS": 2
        },
        "Median": {
            "CHEVRON": 4,
            "CAUTIONARY_WARNING_SIGNS": 2,
            "HAZARD": 1,
            "PROHIBITORY_MANDATORY_SIGNS": 1
        },
        "Center": {},
        "lat": 19.01765948,
        "lng": 84.60945745,
        "to_lat": 19.0141195,
        "to_lng": 84.60644732
    },
    "18585": {
        "Avenue": {
            "CAUTIONARY_WARNING_SIGNS": 1,
            "HAZARD": 1
        },
        "Median": {},
        "Center": {},
        "lat": 19.0141195,
        "lng": 84.60644732,
        "to_lat": 19.01007397,
        "to_lng": 84.60437888
    },
    "19085": {
        "Avenue": {},
        "Median": {},
        "Center": {},
        "lat": 19.01007397,
        "lng": 84.60437888,
        "to_lat": 19.00609103,
        "to_lng": 84.60232152
    },
    "19585": {
        "Avenue": {
            "PROHIBITORY_MANDATORY_SIGNS": 1,
            "INFORMATORY_SIGNS": 3,
            "HAZARD": 1
        },
        "Median": {
            "CAUTIONARY_WARNING_SIGNS": 2
        },
        "Center": {},
        "lat": 19.00609103,
        "lng": 84.60232152,
        "to_lat": 19.00222208,
        "to_lng": 84.59971715
    },
    "20085": {
        "Avenue": {
            "HAZARD": 1
        },
        "Median": {
            "CAUTIONARY_WARNING_SIGNS": 1,
            "PROHIBITORY_MANDATORY_SIGNS": 1,
            "HAZARD": 1
        },
        "Center": {},
        "lat": 19.00222208,
        "lng": 84.59971715,
        "to_lat": 18.99866152,
        "to_lng": 84.59717363
    },
    "20585": {
        "Avenue": {},
        "Median": {},
        "Center": {},
        "lat": 18.99866152,
        "lng": 84.59717363,
        "to_lat": 18.99511763,
        "to_lng": 84.59412138
    },
    "21085": {
        "Avenue": {
            "INFORMATORY_SIGNS": 2,
            "HAZARD": 1
        },
        "Median": {
            "CAUTIONARY_WARNING_SIGNS": 2,
            "PROHIBITORY_MANDATORY_SIGNS": 2
        },
        "Center": {},
        "lat": 18.99511763,
        "lng": 84.59412138,
        "to_lat": 18.99128872,
        "to_lng": 84.59160268
    },
    "21585": {
        "Avenue": {
            "INFORMATORY_SIGNS": 1,
            "HAZARD": 1
        },
        "Median": {
            "CHEVRON": 4
        },
        "Center": {},
        "lat": 18.99128872,
        "lng": 84.59160268,
        "to_lat": 18.98732293,
        "to_lng": 84.589334
    },
    "22085": {
        "Avenue": {
            "CHEVRON": 5,
            "HAZARD": 1
        },
        "Median": {
            "CHEVRON": 4
        },
        "Center": {},
        "lat": 18.98732293,
        "lng": 84.589334,
        "to_lat": 18.98275348,
        "to_lng": 84.58902762
    },
    "22585": {
        "Avenue": {
            "CHEVRON": 2
        },
        "Median": {
            "CAUTIONARY_WARNING_SIGNS": 1
        },
        "Center": {},
        "lat": 18.98275348,
        "lng": 84.58902762,
        "to_lat": 18.97852558,
        "to_lng": 84.58767475
    },
    "23085": {
        "Avenue": {},
        "Median": {},
        "Center": {},
        "lat": 18.97852558,
        "lng": 84.58767475,
        "to_lat": 18.97490817,
        "to_lng": 84.58474025
    },
    "23585": {
        "Avenue": {
            "HAZARD": 2,
            "INFORMATORY_SIGNS": 2
        },
        "Median": {
            "CAUTIONARY_WARNING_SIGNS": 2,
            "INFORMATORY_SIGNS": 1,
            "HAZARD": 1
        },
        "Center": {},
        "lat": 18.97490817,
        "lng": 84.58474025,
        "to_lat": 18.97151005,
        "to_lng": 84.5816467
    },
    "24085": {
        "Avenue": {},
        "Median": {},
        "Center": {},
        "lat": 18.97151005,
        "lng": 84.5816467,
        "to_lat": 18.96819345,
        "to_lng": 84.5784784
    },
    "24585": {
        "Avenue": {
            "HAZARD": 1,
            "CAUTIONARY_WARNING_SIGNS": 1
        },
        "Median": {
            "CHEVRON": 1
        },
        "Center": {},
        "lat": 18.96819345,
        "lng": 84.5784784,
        "to_lat": 18.96559168,
        "to_lng": 84.5746203
    },
    "25085": {
        "Avenue": {},
        "Median": {
            "CHEVRON": 6
        },
        "Center": {},
        "lat": 18.96559168,
        "lng": 84.5746203,
        "to_lat": 18.96217032,
        "to_lng": 84.57169712
    },
    "25585": {
        "Avenue": {
            "CAUTIONARY_WARNING_SIGNS": 2,
            "HAZARD": 3,
            "INFORMATORY_SIGNS": 1
        },
        "Median": {
            "HAZARD": 2
        },
        "Center": {},
        "lat": 18.96217032,
        "lng": 84.57169712,
        "to_lat": 18.95810403,
        "to_lng": 84.56985092
    },
    "26085": {
        "Avenue": {
            "HAZARD": 1,
            "DIGITAL_SPEED_DISPLAY_SIGNS": 1
        },
        "Median": {},
        "Center": {},
        "lat": 18.95810403,
        "lng": 84.56985092,
        "to_lat": 18.95390113,
        "to_lng": 84.5678967
    },
    "26585": {
        "Avenue": {
            "PROHIBITORY_MANDATORY_SIGNS": 1,
            "HAZARD": 1
        },
        "Median": {
            "DIGITAL_SPEED_DISPLAY_SIGNS": 1,
            "CAUTIONARY_WARNING_SIGNS": 2,
            "PROHIBITORY_MANDATORY_SIGNS": 2,
            "HAZARD": 1
        },
        "Center": {},
        "lat": 18.95390113,
        "lng": 84.5678967,
        "to_lat": 18.94973967,
        "to_lng": 84.56596517
    },
    "27085": {
        "Avenue": {},
        "Median": {
            "CHEVRON": 4
        },
        "Center": {},
        "lat": 18.94973967,
        "lng": 84.56596517,
        "to_lat": 18.94557978,
        "to_lng": 84.56423257
    },
    "27585": {
        "Avenue": {
            "HAZARD": 1,
            "CAUTIONARY_WARNING_SIGNS": 1,
            "INFORMATORY_SIGNS": 1
        },
        "Median": {
            "CAUTIONARY_WARNING_SIGNS": 2,
            "INFORMATORY_SIGNS": 1,
            "HAZARD": 1
        },
        "Center": {},
        "lat": 18.94557978,
        "lng": 84.56423257,
        "to_lat": 18.94111855,
        "to_lng": 84.56442815
    },
    "28085": {
        "Avenue": {},
        "Median": {},
        "Center": {},
        "lat": 18.94111855,
        "lng": 84.56442815,
        "to_lat": 18.93669002,
        "to_lng": 84.56379682
    },
    "28585": {
        "Avenue": {
            "HAZARD": 1
        },
        "Median": {},
        "Center": {},
        "lat": 18.93669002,
        "lng": 84.56379682,
        "to_lat": 18.9322311,
        "to_lng": 84.56284075
    },
    "29085": {
        "Avenue": {
            "CAUTIONARY_WARNING_SIGNS": 2,
            "HAZARD": 1
        },
        "Median": {
            "HAZARD": 1
        },
        "Center": {},
        "lat": 18.9322311,
        "lng": 84.56284075,
        "to_lat": 18.92771915,
        "to_lng": 84.56187697
    },
    "29585": {
        "Avenue": {
            "HAZARD": 3,
            "CHEVRON": 1,
            "INFORMATORY_SIGNS": 1
        },
        "Median": {},
        "Center": {},
        "lat": 18.92771915,
        "lng": 84.56187697,
        "to_lat": 18.92345185,
        "to_lng": 84.56049382
    },
    "30085": {
        "Avenue": {
            "CAUTIONARY_WARNING_SIGNS": 2,
            "INFORMATORY_SIGNS": 2
        },
        "Median": {
            "CAUTIONARY_WARNING_SIGNS": 2,
            "PROHIBITORY_MANDATORY_SIGNS": 1,
            "HAZARD": 1
        },
        "Center": {},
        "lat": 18.92345185,
        "lng": 84.56049382,
        "to_lat": 18.91927373,
        "to_lng": 84.55884523
    },
    "30585": {
        "Avenue": {
            "HAZARD": 2,
            "PROHIBITORY_MANDATORY_SIGNS": 1
        },
        "Median": {},
        "Center": {},
        "lat": 18.91927373,
        "lng": 84.55884523,
        "to_lat": 18.91512828,
        "to_lng": 84.55720153
    },
    "31085": {
        "Avenue": {
            "HAZARD": 1
        },
        "Median": {},
        "Center": {},
        "lat": 18.91512828,
        "lng": 84.55720153,
        "to_lat": 18.91081433,
        "to_lng": 84.5557797
    },
    "31585": {
        "Avenue": {
            "HAZARD": 3,
            "CAUTIONARY_WARNING_SIGNS": 1,
            "INFORMATORY_SIGNS": 2,
            "PROHIBITORY_MANDATORY_SIGNS": 1
        },
        "Median": {
            "CAUTIONARY_WARNING_SIGNS": 3,
            "HAZARD": 1
        },
        "Center": {},
        "lat": 18.91081433,
        "lng": 84.5557797,
        "to_lat": 18.90653638,
        "to_lng": 84.55423262
    },
    "32085": {
        "Avenue": {
            "INFORMATORY_SIGNS": 1,
            "HAZARD": 1
        },
        "Median": {},
        "Center": {},
        "lat": 18.90653638,
        "lng": 84.55423262,
        "to_lat": 18.90248353,
        "to_lng": 84.55238398
    },
    "32585": {
        "Avenue": {
            "PROHIBITORY_MANDATORY_SIGNS": 1
        },
        "Median": {},
        "Center": {},
        "lat": 18.90248353,
        "lng": 84.55238398,
        "to_lat": 18.89824372,
        "to_lng": 84.55053705
    },
    "33085": {
        "Avenue": {
            "HAZARD": 1,
            "PROHIBITORY_MANDATORY_SIGNS": 1,
            "CHEVRON": 2
        },
        "Median": {},
        "Center": {},
        "lat": 18.89824372,
        "lng": 84.55053705,
        "to_lat": 18.89386342,
        "to_lng": 84.54901042
    },
    "33585": {
        "Avenue": {
            "CHEVRON": 6
        },
        "Median": {},
        "Center": {},
        "lat": 18.89386342,
        "lng": 84.54901042,
        "to_lat": 18.89122072,
        "to_lng": 84.54552527
    },
    "34085": {
        "Avenue": {
            "INFORMATORY_SIGNS": 3,
            "CAUTIONARY_WARNING_SIGNS": 1
        },
        "Median": {
            "CHEVRON": 1
        },
        "Center": {},
        "lat": 18.89122072,
        "lng": 84.54552527,
        "to_lat": 18.8890276,
        "to_lng": 84.5411926
    },
    "34585": {
        "Avenue": {
            "HAZARD": 3,
            "CAUTIONARY_WARNING_SIGNS": 1
        },
        "Median": {
            "CHEVRON": 2
        },
        "Center": {},
        "lat": 18.8890276,
        "lng": 84.5411926,
        "to_lat": 18.88639363,
        "to_lng": 84.53741405
    },
    "35085": {
        "Avenue": {
            "CAUTIONARY_WARNING_SIGNS": 1,
            "PROHIBITORY_MANDATORY_SIGNS": 1,
            "HAZARD": 1
        },
        "Median": {
            "HAZARD": 1
        },
        "Center": {},
        "lat": 18.88639363,
        "lng": 84.53741405,
        "to_lat": 18.883103,
        "to_lng": 84.53409603
    },
    "35585": {
        "Avenue": {},
        "Median": {},
        "Center": {},
        "lat": 18.883103,
        "lng": 84.53409603,
        "to_lat": 18.88006615,
        "to_lng": 84.53083535
    },
    "36085": {
        "Avenue": {
            "HAZARD": 1
        },
        "Median": {
            "HAZARD": 1
        },
        "Center": {},
        "lat": 18.88006615,
        "lng": 84.53083535,
        "to_lat": 18.8767114,
        "to_lng": 84.52738128
    },
    "36585": {
        "Avenue": {
            "INFORMATORY_SIGNS": 1
        },
        "Median": {},
        "Center": {},
        "lat": 18.8767114,
        "lng": 84.52738128,
        "to_lat": 18.87363863,
        "to_lng": 84.5241866
    },
    "37085": {
        "Avenue": {
            "INFORMATORY_SIGNS": 1
        },
        "Median": {
            "HAZARD": 1
        },
        "Center": {},
        "lat": 18.87363863,
        "lng": 84.5241866,
        "to_lat": 18.87103002,
        "to_lng": 84.52019777
    },
    "37585": {
        "Avenue": {
            "INFORMATORY_SIGNS": 3,
            "HAZARD": 1
        },
        "Median": {
            "CAUTIONARY_WARNING_SIGNS": 2,
            "PROHIBITORY_MANDATORY_SIGNS": 1
        },
        "Center": {},
        "lat": 18.87103002,
        "lng": 84.52019777,
        "to_lat": 18.86872172,
        "to_lng": 84.51614022
    },
    "38085": {
        "Avenue": {
            "HAZARD": 1
        },
        "Median": {},
        "Center": {},
        "lat": 18.86872172,
        "lng": 84.51614022,
        "to_lat": 18.86637143,
        "to_lng": 84.51206652
    },
    "38585": {
        "Avenue": {
            "HAZARD": 2,
            "CAUTIONARY_WARNING_SIGNS": 1,
            "INFORMATORY_SIGNS": 1
        },
        "Median": {},
        "Center": {},
        "lat": 18.86637143,
        "lng": 84.51206652,
        "to_lat": 18.86392233,
        "to_lng": 84.50796178
    },
    "39085": {
        "Avenue": {
            "HAZARD": 1,
            "CAUTIONARY_WARNING_SIGNS": 1
        },
        "Median": {},
        "Center": {},
        "lat": 18.86392233,
        "lng": 84.50796178,
        "to_lat": 18.8607356,
        "to_lng": 84.50476065
    },
    "39585": {
        "Avenue": {
            "INFORMATORY_SIGNS": 2
        },
        "Median": {},
        "Center": {},
        "lat": 18.8607356,
        "lng": 84.50476065,
        "to_lat": 18.85727153,
        "to_lng": 84.5017402
    },
    "40085": {
        "Avenue": {
            "HAZARD": 2
        },
        "Median": {
            "HAZARD": 1
        },
        "Center": {},
        "lat": 18.85727153,
        "lng": 84.5017402,
        "to_lat": 18.85378712,
        "to_lng": 84.49871723
    },
    "40585": {
        "Avenue": {
            "HAZARD": 1
        },
        "Median": {
            "HAZARD": 1
        },
        "Center": {},
        "lat": 18.85378712,
        "lng": 84.49871723,
        "to_lat": 18.85029648,
        "to_lng": 84.49568162
    },
    "41085": {
        "Avenue": {
            "CAUTIONARY_WARNING_SIGNS": 2
        },
        "Median": {
            "PROHIBITORY_MANDATORY_SIGNS": 1,
            "CAUTIONARY_WARNING_SIGNS": 2,
            "HAZARD": 1
        },
        "Center": {},
        "lat": 18.85029648,
        "lng": 84.49568162,
        "to_lat": 18.84682603,
        "to_lng": 84.49258502
    },
    "41585": {
        "Avenue": {
            "CAUTIONARY_WARNING_SIGNS": 1,
            "INFORMATORY_SIGNS": 1,
            "HAZARD": 1,
            "DAMAGED_SIGN": 1
        },
        "Median": {},
        "Center": {},
        "lat": 18.84682603,
        "lng": 84.49258502,
        "to_lat": 18.8432617,
        "to_lng": 84.48958517
    },
    "42085": {
        "Avenue": {
            "HAZARD": 1,
            "PROHIBITORY_MANDATORY_SIGNS": 1
        },
        "Median": {},
        "Center": {},
        "lat": 18.8432617,
        "lng": 84.48958517,
        "to_lat": 18.83923742,
        "to_lng": 84.48762218
    },
    "42585": {
        "Avenue": {
            "HAZARD": 1,
            "PROHIBITORY_MANDATORY_SIGNS": 1,
            "CHEVRON": 1,
            "DAMAGED_SIGN": 1
        },
        "Median": {},
        "Center": {},
        "lat": 18.83923742,
        "lng": 84.48762218,
        "to_lat": 18.83502657,
        "to_lng": 84.48583212
    },
    "43085": {
        "Avenue": {
            "CHEVRON": 6
        },
        "Median": {},
        "Center": {},
        "lat": 18.83502657,
        "lng": 84.48583212,
        "to_lat": 18.83130222,
        "to_lng": 84.4835322
    },
    "43585": {
        "Avenue": {
            "CHEVRON": 1,
            "PROHIBITORY_MANDATORY_SIGNS": 1,
            "INFORMATORY_SIGNS": 1,
            "HAZARD": 1
        },
        "Median": {
            "CHEVRON": 1
        },
        "Center": {},
        "lat": 18.83130222,
        "lng": 84.4835322,
        "to_lat": 18.82809295,
        "to_lng": 84.48003838
    },
    "44085": {
        "Avenue": {
            "INFORMATORY_SIGNS": 1,
            "PROHIBITORY_MANDATORY_SIGNS": 1
        },
        "Median": {
            "CHEVRON": 1
        },
        "Center": {},
        "lat": 18.82809295,
        "lng": 84.48003838,
        "to_lat": 18.82434842,
        "to_lng": 84.47750382
    },
    "44585": {
        "Avenue": {
            "CAUTIONARY_WARNING_SIGNS": 1,
            "PROHIBITORY_MANDATORY_SIGNS": 1,
            "INFORMATORY_SIGNS": 1
        },
        "Median": {
            "HAZARD": 2,
            "PROHIBITORY_MANDATORY_SIGNS": 1,
            "CAUTIONARY_WARNING_SIGNS": 1
        },
        "Center": {},
        "lat": 18.82434842,
        "lng": 84.47750382,
        "to_lat": 18.82035637,
        "to_lng": 84.47514343
    },
    "45085": {
        "Avenue": {
            "CHEVRON": 4,
            "INFORMATORY_SIGNS": 1
        },
        "Median": {
            "CAUTIONARY_WARNING_SIGNS": 1,
            "INFORMATORY_SIGNS": 1
        },
        "Center": {},
        "lat": 18.82035637,
        "lng": 84.47514343,
        "to_lat": 18.81630895,
        "to_lng": 84.47300435
    },
    "45585": {
        "Avenue": {
            "CHEVRON": 3,
            "CAUTIONARY_WARNING_SIGNS": 3,
            "INFORMATORY_SIGNS": 3,
            "HAZARD": 1
        },
        "Median": {
            "PROHIBITORY_MANDATORY_SIGNS": 1,
            "HAZARD": 1
        },
        "Center": {},
        "lat": 18.81630895,
        "lng": 84.47300435,
        "to_lat": 18.81322085,
        "to_lng": 84.46958217
    },
    "46085": {
        "Avenue": {
            "HAZARD": 1,
            "INFORMATORY_SIGNS": 1
        },
        "Median": {
            "CHEVRON": 7
        },
        "Center": {},
        "lat": 18.81322085,
        "lng": 84.46958217,
        "to_lat": 18.81002952,
        "to_lng": 84.4664176
    },
    "46585": {
        "Avenue": {},
        "Median": {
            "HAZARD": 1
        },
        "Center": {},
        "lat": 18.81002952,
        "lng": 84.4664176,
        "to_lat": 18.80639013,
        "to_lng": 84.46365805
    },
    "47085": {
        "Avenue": {},
        "Median": {},
        "Center": {},
        "lat": 18.80639013,
        "lng": 84.46365805,
        "to_lat": 18.80250893,
        "to_lng": 84.46136692
    },
    "47585": {
        "Avenue": {},
        "Median": {},
        "Center": {},
        "lat": 18.80250893,
        "lng": 84.46136692,
        "to_lat": 18.80121537,
        "to_lng": 84.45693893
    },
    "48085": {
        "Avenue": {},
        "Median": {},
        "Center": {},
        "lat": 18.80121537,
        "lng": 84.45693893,
        "to_lat": 18.79755438,
        "to_lng": 84.4543633
    },
    "48585": {
        "Avenue": {},
        "Median": {},
        "Center": {},
        "lat": 18.79755438,
        "lng": 84.4543633,
        "to_lat": 18.79332102,
        "to_lng": 84.45279297
    },
    "49085": {
        "Avenue": {},
        "Median": {},
        "Center": {},
        "lat": 18.79332102,
        "lng": 84.45279297,
        "to_lat": 18.78954658,
        "to_lng": 84.45029482
    },
    "49585": {
        "Avenue": {},
        "Median": {},
        "Center": {},
        "lat": 18.78954658,
        "lng": 84.45029482,
        "to_lat": 18.78694773,
        "to_lng": 84.44656668
    },
    "50085": {
        "Avenue": {},
        "Median": {},
        "Center": {},
        "lat": 18.78694773,
        "lng": 84.44656668,
        "to_lat": 18.78671008,
        "to_lng": 84.44181708
    },
    "50585": {
        "Avenue": {},
        "Median": {},
        "Center": {},
        "lat": 18.78671008,
        "lng": 84.44181708,
        "to_lat": 18.78578663,
        "to_lng": 84.43713442
    },
    "51085": {
        "Avenue": {},
        "Median": {},
        "Center": {},
        "lat": 18.78578663,
        "lng": 84.43713442,
        "to_lat": 18.78520467,
        "to_lng": 84.43250172
    },
    "51585": {
        "Avenue": {},
        "Median": {},
        "Center": {},
        "lat": 18.78520467,
        "lng": 84.43250172,
        "to_lat": 18.78465925,
        "to_lng": 84.427829
    },
    "52085": {
        "Avenue": {
            "HAZARD": 1
        },
        "Median": {},
        "Center": {},
        "lat": 18.78465925,
        "lng": 84.427829,
        "to_lat": 18.78393352,
        "to_lng": 84.42308708
    },
    "52585": {
        "Avenue": {
            "INFORMATORY_SIGNS": 1
        },
        "Median": {},
        "Center": {},
        "lat": 18.78393352,
        "lng": 84.42308708,
        "to_lat": 18.7830192,
        "to_lng": 84.41851573
    },
    "53085": {
        "Avenue": {
            "HAZARD": 1
        },
        "Median": {
            "HAZARD": 1
        },
        "Center": {},
        "lat": 18.7830192,
        "lng": 84.41851573,
        "to_lat": 18.78209982,
        "to_lng": 84.4137892
    },
    "53585": {
        "Avenue": {
            "PROHIBITORY_MANDATORY_SIGNS": 1,
            "CAUTIONARY_WARNING_SIGNS": 1
        },
        "Median": {
            "CAUTIONARY_WARNING_SIGNS": 2
        },
        "Center": {},
        "lat": 18.78209982,
        "lng": 84.4137892,
        "to_lat": 18.7810665,
        "to_lng": 84.40932512
    },
    "54085": {
        "Avenue": {
            "INFORMATORY_SIGNS": 2,
            "CAUTIONARY_WARNING_SIGNS": 1,
            "HAZARD": 1
        },
        "Median": {
            "HAZARD": 2,
            "CHEVRON": 2
        },
        "Center": {},
        "lat": 18.7810665,
        "lng": 84.40932512,
        "to_lat": 18.77980035,
        "to_lng": 84.40467967
    },
    "54585": {
        "Avenue": {
            "HAZARD": 1
        },
        "Median": {
            "CHEVRON": 4
        },
        "Center": {},
        "lat": 18.77980035,
        "lng": 84.40467967,
        "to_lat": 18.77741367,
        "to_lng": 84.40078367
    },
    "55085": {
        "Avenue": {
            "HAZARD": 1
        },
        "Median": {},
        "Center": {},
        "lat": 18.77741367,
        "lng": 84.40078367,
        "to_lat": 18.77373053,
        "to_lng": 84.39792363
    },
    "55585": {
        "Avenue": {
            "HAZARD": 1,
            "INFORMATORY_SIGNS": 1,
            "PROHIBITORY_MANDATORY_SIGNS": 1
        },
        "Median": {
            "CHEVRON": 2,
            "PROHIBITORY_MANDATORY_SIGNS": 1
        },
        "Center": {},
        "lat": 18.77373053,
        "lng": 84.39792363,
        "to_lat": 18.76937692,
        "to_lng": 84.39665588
    },
    "56085": {
        "Avenue": {
            "HAZARD": 1,
            "PROHIBITORY_MANDATORY_SIGNS": 1
        },
        "Median": {
            "HAZARD": 1,
            "CHEVRON": 6
        },
        "Center": {},
        "lat": 18.76937692,
        "lng": 84.39665588,
        "to_lat": 18.76494313,
        "to_lng": 84.3970719
    },
    "56585": {
        "Avenue": {
            "CAUTIONARY_WARNING_SIGNS": 1,
            "PROHIBITORY_MANDATORY_SIGNS": 1
        },
        "Median": {},
        "Center": {},
        "lat": 18.76494313,
        "lng": 84.3970719,
        "to_lat": 18.76054542,
        "to_lng": 84.39806573
    },
    "57085": {
        "Avenue": {},
        "Median": {},
        "Center": {},
        "lat": 18.76054542,
        "lng": 84.39806573,
        "to_lat": 18.75605412,
        "to_lng": 84.39903462
    },
    "57585": {
        "Avenue": {
            "CAUTIONARY_WARNING_SIGNS": 1,
            "INFORMATORY_SIGNS": 1,
            "DAMAGED_SIGN": 1
        },
        "Median": {
            "INFORMATORY_SIGNS": 1,
            "CAUTIONARY_WARNING_SIGNS": 1
        },
        "Center": {},
        "lat": 18.75605412,
        "lng": 84.39903462,
        "to_lat": 18.75178325,
        "to_lng": 84.4001507
    },
    "58085": {
        "Avenue": {
            "CHEVRON": 5,
            "HAZARD": 1
        },
        "Median": {
            "HAZARD": 1
        },
        "Center": {},
        "lat": 18.75178325,
        "lng": 84.4001507,
        "to_lat": 18.74748468,
        "to_lng": 84.40121735
    },
    "58585": {
        "Avenue": {
            "CHEVRON": 5,
            "INFORMATORY_SIGNS": 2
        },
        "Median": {},
        "Center": {},
        "lat": 18.74748468,
        "lng": 84.40121735,
        "to_lat": 18.74344283,
        "to_lng": 84.39909473
    },
    "59085": {
        "Avenue": {
            "CAUTIONARY_WARNING_SIGNS": 1
        },
        "Median": {},
        "Center": {},
        "lat": 18.74344283,
        "lng": 84.39909473,
        "to_lat": 18.7401104,
        "to_lng": 84.39602695
    },
    "59585": {
        "Avenue": {
            "PROHIBITORY_MANDATORY_SIGNS": 1,
            "INFORMATORY_SIGNS": 1
        },
        "Median": {},
        "Center": {},
        "lat": 18.7401104,
        "lng": 84.39602695,
        "to_lat": 18.73668552,
        "to_lng": 84.39277403
    },
    "60085": {
        "Avenue": {
            "INFORMATORY_SIGNS": 11
        },
        "Median": {
            "PROHIBITORY_MANDATORY_SIGNS": 1
        },
        "Center": {},
        "lat": 18.73668552,
        "lng": 84.39277403,
        "to_lat": 18.73312912,
        "to_lng": 84.38971078
    },
    "60585": {
        "Avenue": {
            "HAZARD": 1,
            "INFORMATORY_SIGNS": 1
        },
        "Median": {
            "PROHIBITORY_MANDATORY_SIGNS": 1,
            "HAZARD": 1
        },
        "Center": {},
        "lat": 18.73312912,
        "lng": 84.38971078,
        "to_lat": 18.72995288,
        "to_lng": 84.38652335
    },
    "61085": {
        "Avenue": {
            "INFORMATORY_SIGNS": 2,
            "PROHIBITORY_MANDATORY_SIGNS": 1
        },
        "Median": {},
        "Center": {},
        "lat": 18.72995288,
        "lng": 84.38652335,
        "to_lat": 18.72654203,
        "to_lng": 84.38334877
    },
    "61585": {
        "Avenue": {
            "CHEVRON": 1
        },
        "Median": {
            "HAZARD": 1
        },
        "Center": {},
        "lat": 18.72654203,
        "lng": 84.38334877,
        "to_lat": 18.72326657,
        "to_lng": 84.38019312
    },
    "62085": {
        "Avenue": {
            "CHEVRON": 5,
            "CAUTIONARY_WARNING_SIGNS": 1,
            "PROHIBITORY_MANDATORY_SIGNS": 1
        },
        "Median": {},
        "Center": {},
        "lat": 18.72326657,
        "lng": 84.38019312,
        "to_lat": 18.72119902,
        "to_lng": 84.37606075
    },
    "62585": {
        "Avenue": {
            "INFORMATORY_SIGNS": 2,
            "HAZARD": 2
        },
        "Median": {},
        "Center": {},
        "lat": 18.72119902,
        "lng": 84.37606075,
        "to_lat": 18.72019887,
        "to_lng": 84.37146405
    },
    "63085": {
        "Avenue": {
            "CAUTIONARY_WARNING_SIGNS": 1,
            "HAZARD": 1
        },
        "Median": {},
        "Center": {},
        "lat": 18.72019887,
        "lng": 84.37146405,
        "to_lat": 18.71924533,
        "to_lng": 84.36697672
    },
    "63585": {
        "Avenue": {
            "INFORMATORY_SIGNS": 2,
            "CAUTIONARY_WARNING_SIGNS": 1
        },
        "Median": {
            "INFORMATORY_SIGNS": 1
        },
        "Center": {},
        "lat": 18.71924533,
        "lng": 84.36697672,
        "to_lat": 18.71826755,
        "to_lng": 84.36228425
    },
    "64085": {
        "Avenue": {
            "INFORMATORY_SIGNS": 1,
            "HAZARD": 3,
            "CAUTIONARY_WARNING_SIGNS": 1,
            "PROHIBITORY_MANDATORY_SIGNS": 2
        },
        "Median": {
            "HAZARD": 1
        },
        "Center": {},
        "lat": 18.71826755,
        "lng": 84.36228425,
        "to_lat": 18.71724642,
        "to_lng": 84.35756752
    },
    "64585": {
        "Avenue": {
            "PROHIBITORY_MANDATORY_SIGNS": 1
        },
        "Median": {
            "CAUTIONARY_WARNING_SIGNS": 1
        },
        "Center": {},
        "lat": 18.71724642,
        "lng": 84.35756752,
        "to_lat": 18.7163816,
        "to_lng": 84.35290182
    },
    "65085": {
        "Avenue": {
            "CAUTIONARY_WARNING_SIGNS": 1,
            "CHEVRON": 2,
            "HAZARD": 1,
            "PROHIBITORY_MANDATORY_SIGNS": 1
        },
        "Median": {
            "INFORMATORY_SIGNS": 1,
            "CHEVRON": 5,
            "CAUTIONARY_WARNING_SIGNS": 1,
            "HAZARD": 1
        },
        "Center": {},
        "lat": 18.7163816,
        "lng": 84.35290182,
        "to_lat": 18.71567705,
        "to_lng": 84.34825453
    },
    "65585": {
        "Avenue": {
            "HAZARD": 1
        },
        "Median": {
            "CHEVRON": 2
        },
        "Center": {},
        "lat": 18.71567705,
        "lng": 84.34825453,
        "to_lat": 18.71270512,
        "to_lng": 84.34495842
    },
    "66085": {
        "Avenue": {
            "INFORMATORY_SIGNS": 1,
            "PROHIBITORY_MANDATORY_SIGNS": 1
        },
        "Median": {
            "INFORMATORY_SIGNS": 1
        },
        "Center": {},
        "lat": 18.71270512,
        "lng": 84.34495842,
        "to_lat": 18.70932292,
        "to_lng": 84.34187722
    },
    "66585": {
        "Avenue": {
            "PROHIBITORY_MANDATORY_SIGNS": 2,
            "CHEVRON": 4
        },
        "Median": {},
        "Center": {},
        "lat": 18.70932292,
        "lng": 84.34187722,
        "to_lat": 18.70559078,
        "to_lng": 84.33898442
    },
    "67085": {
        "Avenue": {
            "INFORMATORY_SIGNS": 1,
            "CAUTIONARY_WARNING_SIGNS": 2,
            "HAZARD": 1
        },
        "Median": {
            "HAZARD": 1
        },
        "Center": {},
        "lat": 18.70559078,
        "lng": 84.33898442,
        "to_lat": 18.70221245,
        "to_lng": 84.33589112
    },
    "67585": {
        "Avenue": {},
        "Median": {},
        "Center": {},
        "lat": 18.70221245,
        "lng": 84.33589112,
        "to_lat": 18.69874148,
        "to_lng": 84.33271705
    },
    "68085": {
        "Avenue": {
            "INFORMATORY_SIGNS": 2,
            "CAUTIONARY_WARNING_SIGNS": 1
        },
        "Median": {
            "CAUTIONARY_WARNING_SIGNS": 2,
            "INFORMATORY_SIGNS": 1,
            "PROHIBITORY_MANDATORY_SIGNS": 1,
            "HAZARD": 1,
            "CHEVRON": 2
        },
        "Center": {},
        "lat": 18.69874148,
        "lng": 84.33271705,
        "to_lat": 18.69537277,
        "to_lng": 84.32967668
    },
    "68585": {
        "Avenue": {},
        "Median": {
            "CHEVRON": 2
        },
        "Center": {},
        "lat": 18.69537277,
        "lng": 84.32967668,
        "to_lat": 18.69172053,
        "to_lng": 84.32701055
    },
    "69085": {
        "Avenue": {
            "CAUTIONARY_WARNING_SIGNS": 1
        },
        "Median": {},
        "Center": {},
        "lat": 18.69172053,
        "lng": 84.32701055,
        "to_lat": 18.68780703,
        "to_lng": 84.32446318
    },
    "69585": {
        "Avenue": {
            "HAZARD": 1,
            "CAUTIONARY_WARNING_SIGNS": 1,
            "INFORMATORY_SIGNS": 2
        },
        "Median": {
            "CAUTIONARY_WARNING_SIGNS": 2,
            "PROHIBITORY_MANDATORY_SIGNS": 1
        },
        "Center": {},
        "lat": 18.68780703,
        "lng": 84.32446318,
        "to_lat": 18.68391065,
        "to_lng": 84.3222893
    },
    "70085": {
        "Avenue": {
            "INFORMATORY_SIGNS": 1,
            "HAZARD": 2
        },
        "Median": {
            "HAZARD": 1
        },
        "Center": {},
        "lat": 18.68391065,
        "lng": 84.3222893,
        "to_lat": 18.68003597,
        "to_lng": 84.32011065
    },
    "70585": {
        "Avenue": {
            "HAZARD": 2
        },
        "Median": {},
        "Center": {},
        "lat": 18.68003597,
        "lng": 84.32011065,
        "to_lat": 18.67592255,
        "to_lng": 84.31789775
    },
    "71085": {
        "Avenue": {
            "CAUTIONARY_WARNING_SIGNS": 1
        },
        "Median": {},
        "Center": {},
        "lat": 18.67592255,
        "lng": 84.31789775,
        "to_lat": 18.67164083,
        "to_lng": 84.31591375
    },
    "71585": {
        "Avenue": {
            "CAUTIONARY_WARNING_SIGNS": 2,
            "PROHIBITORY_MANDATORY_SIGNS": 1,
            "CHEVRON": 6,
            "HAZARD": 1,
            "INFORMATORY_SIGNS": 1
        },
        "Median": {
            "HAZARD": 1
        },
        "Center": {},
        "lat": 18.67164083,
        "lng": 84.31591375,
        "to_lat": 18.66786698,
        "to_lng": 84.3135137
    },
    "72085": {
        "Avenue": {
            "INFORMATORY_SIGNS": 2,
            "HAZARD": 2,
            "PROHIBITORY_MANDATORY_SIGNS": 2,
            "CAUTIONARY_WARNING_SIGNS": 2
        },
        "Median": {
            "INFORMATORY_SIGNS": 1
        },
        "Center": {},
        "lat": 18.66786698,
        "lng": 84.3135137,
        "to_lat": 18.6647267,
        "to_lng": 84.31017455
    },
    "72585": {
        "Avenue": {
            "HAZARD": 1
        },
        "Median": {
            "CAUTIONARY_WARNING_SIGNS": 2,
            "INFORMATORY_SIGNS": 1,
            "HAZARD": 1
        },
        "Center": {},
        "lat": 18.6647267,
        "lng": 84.31017455,
        "to_lat": 18.66161505,
        "to_lng": 84.30678365
    },
    "73085": {
        "Avenue": {
            "INFORMATORY_SIGNS": 2,
            "PROHIBITORY_MANDATORY_SIGNS": 1,
            "HAZARD": 3
        },
        "Median": {},
        "Center": {},
        "lat": 18.66161505,
        "lng": 84.30678365,
        "to_lat": 18.65852705,
        "to_lng": 84.30337837
    },
    "73585": {
        "Avenue": {
            "PROHIBITORY_MANDATORY_SIGNS": 1
        },
        "Median": {},
        "Center": {},
        "lat": 18.65852705,
        "lng": 84.30337837,
        "to_lat": 18.65601427,
        "to_lng": 84.29941773
    },
    "74085": {
        "Avenue": {
            "CAUTIONARY_WARNING_SIGNS": 3,
            "PROHIBITORY_MANDATORY_SIGNS": 2,
            "HAZARD": 1,
            "INFORMATORY_SIGNS": 1
        },
        "Median": {
            "CHEVRON": 4,
            "HAZARD": 1
        },
        "Center": {},
        "lat": 18.65601427,
        "lng": 84.29941773,
        "to_lat": 18.65574923,
        "to_lng": 84.29476417
    },
    "74585": {
        "Avenue": {
            "CAUTIONARY_WARNING_SIGNS": 1
        },
        "Median": {
            "CHEVRON": 1
        },
        "Center": {},
        "lat": 18.65574923,
        "lng": 84.29476417,
        "to_lat": 18.65366402,
        "to_lng": 84.29068725
    },
    "75085": {
        "Avenue": {
            "HAZARD": 1
        },
        "Median": {
            "INFORMATORY_SIGNS": 1,
            "CAUTIONARY_WARNING_SIGNS": 3,
            "PROHIBITORY_MANDATORY_SIGNS": 1,
            "HAZARD": 1
        },
        "Center": {},
        "lat": 18.65366402,
        "lng": 84.29068725,
        "to_lat": 18.65173153,
        "to_lng": 84.28634977
    },
    "75585": {
        "Avenue": {
            "INFORMATORY_SIGNS": 1
        },
        "Median": {},
        "Center": {},
        "lat": 18.65173153,
        "lng": 84.28634977,
        "to_lat": 18.65002198,
        "to_lng": 84.28197642
    },
    "76085": {
        "Avenue": {
            "HAZARD": 1,
            "CAUTIONARY_WARNING_SIGNS": 1
        },
        "Median": {
            "CHEVRON": 3,
            "HAZARD": 1
        },
        "Center": {},
        "lat": 18.65002198,
        "lng": 84.28197642,
        "to_lat": 18.64827472,
        "to_lng": 84.27748592
    },
    "76585": {
        "Avenue": {
            "PROHIBITORY_MANDATORY_SIGNS": 1
        },
        "Median": {
            "CHEVRON": 3
        },
        "Center": {},
        "lat": 18.64827472,
        "lng": 84.27748592,
        "to_lat": 18.6452755,
        "to_lng": 84.27406675
    },
    "77085": {
        "Avenue": {
            "PROHIBITORY_MANDATORY_SIGNS": 2,
            "CAUTIONARY_WARNING_SIGNS": 1,
            "HAZARD": 1
        },
        "Median": {
            "HAZARD": 1
        },
        "Center": {},
        "lat": 18.6452755,
        "lng": 84.27406675,
        "to_lat": 18.64179855,
        "to_lng": 84.27110287
    },
    "77585": {
        "Avenue": {
            "HAZARD": 3,
            "CAUTIONARY_WARNING_SIGNS": 2,
            "INFORMATORY_SIGNS": 3
        },
        "Median": {
            "HAZARD": 1
        },
        "Center": {},
        "lat": 18.64179855,
        "lng": 84.27110287,
        "to_lat": 18.63847182,
        "to_lng": 84.26787732
    },
    "78085": {
        "Avenue": {
            "INFORMATORY_SIGNS": 3,
            "PROHIBITORY_MANDATORY_SIGNS": 2
        },
        "Median": {},
        "Center": {},
        "lat": 18.63847182,
        "lng": 84.26787732,
        "to_lat": 18.6353577,
        "to_lng": 84.26449303
    },
    "78585": {
        "Avenue": {
            "PROHIBITORY_MANDATORY_SIGNS": 1
        },
        "Median": {},
        "Center": {},
        "lat": 18.6353577,
        "lng": 84.26449303,
        "to_lat": 18.63235895,
        "to_lng": 84.26094388
    },
    "79085": {
        "Avenue": {
            "CAUTIONARY_WARNING_SIGNS": 2,
            "HAZARD": 1
        },
        "Median": {
            "HAZARD": 1
        },
        "Center": {},
        "lat": 18.63235895,
        "lng": 84.26094388,
        "to_lat": 18.62959607,
        "to_lng": 84.2572896
    },
    "79585": {
        "Avenue": {
            "CAUTIONARY_WARNING_SIGNS": 1,
            "CHEVRON": 4
        },
        "Median": {
            "HAZARD": 1
        },
        "Center": {},
        "lat": 18.62959607,
        "lng": 84.2572896,
        "to_lat": 18.6267246,
        "to_lng": 84.2536829
    },
    "80085": {
        "Avenue": {
            "HAZARD": 1
        },
        "Median": {
            "CHEVRON": 2
        },
        "Center": {},
        "lat": 18.6267246,
        "lng": 84.2536829,
        "to_lat": 18.62357828,
        "to_lng": 84.2503345
    },
    "80585": {
        "Avenue": {
            "CAUTIONARY_WARNING_SIGNS": 1,
            "PROHIBITORY_MANDATORY_SIGNS": 1,
            "INFORMATORY_SIGNS": 1,
            "HAZARD": 2,
            "CHEVRON": 1
        },
        "Median": {},
        "Center": {},
        "lat": 18.62357828,
        "lng": 84.2503345,
        "to_lat": 18.62079702,
        "to_lng": 84.24680258
    },
    "81085": {
        "Avenue": {
            "CHEVRON": 6
        },
        "Median": {
            "CHEVRON": 1
        },
        "Center": {},
        "lat": 18.62079702,
        "lng": 84.24680258,
        "to_lat": 18.61888918,
        "to_lng": 84.2425342
    },
    "81585": {
        "Avenue": {
            "INFORMATORY_SIGNS": 1,
            "HAZARD": 1
        },
        "Median": {
            "CHEVRON": 4,
            "HAZARD": 1
        },
        "Center": {},
        "lat": 18.61888918,
        "lng": 84.2425342,
        "to_lat": 18.61787348,
        "to_lng": 84.2377947
    },
    "82085": {
        "Avenue": {
            "HAZARD": 1,
            "CAUTIONARY_WARNING_SIGNS": 2,
            "PROHIBITORY_MANDATORY_SIGNS": 2
        },
        "Median": {
            "CHEVRON": 2
        },
        "Center": {},
        "lat": 18.61787348,
        "lng": 84.2377947,
        "to_lat": 18.61525245,
        "to_lng": 84.23413672
    },
    "82585": {
        "Avenue": {
            "CHEVRON": 1,
            "HAZARD": 1,
            "INFORMATORY_SIGNS": 2,
            "CAUTIONARY_WARNING_SIGNS": 1
        },
        "Median": {},
        "Center": {},
        "lat": 18.61525245,
        "lng": 84.23413672,
        "to_lat": 18.6131064,
        "to_lng": 84.22994457
    },
    "83085": {
        "Avenue": {
            "CAUTIONARY_WARNING_SIGNS": 2,
            "INFORMATORY_SIGNS": 2
        },
        "Median": {
            "CHEVRON": 4
        },
        "Center": {},
        "lat": 18.6131064,
        "lng": 84.22994457,
        "to_lat": 18.61124198,
        "to_lng": 84.22567567
    },
    "83585": {
        "Avenue": {
            "INFORMATORY_SIGNS": 1,
            "HAZARD": 1,
            "PROHIBITORY_MANDATORY_SIGNS": 1
        },
        "Median": {
            "CHEVRON": 3
        },
        "Center": {},
        "lat": 18.61124198,
        "lng": 84.22567567,
        "to_lat": 18.60717277,
        "to_lng": 84.22367222
    },
    "84085": {
        "Avenue": {
            "HAZARD": 1,
            "INFORMATORY_SIGNS": 1,
            "CAUTIONARY_WARNING_SIGNS": 1
        },
        "Median": {},
        "Center": {},
        "lat": 18.60717277,
        "lng": 84.22367222,
        "to_lat": 18.60290473,
        "to_lng": 84.22220917
    },
    "84585": {
        "Avenue": {
            "CAUTIONARY_WARNING_SIGNS": 1,
            "PROHIBITORY_MANDATORY_SIGNS": 1
        },
        "Median": {},
        "Center": {},
        "lat": 18.60290473,
        "lng": 84.22220917,
        "to_lat": 18.5987021,
        "to_lng": 84.2207676
    },
    "85085": {
        "Avenue": {
            "INFORMATORY_SIGNS": 1,
            "PROHIBITORY_MANDATORY_SIGNS": 2,
            "CHEVRON": 3,
            "DAMAGED_SIGN": 1
        },
        "Median": {
            "HAZARD": 2
        },
        "Center": {},
        "lat": 18.5987021,
        "lng": 84.2207676,
        "to_lat": 18.5943178,
        "to_lng": 84.21922225
    },
    "85585": {
        "Avenue": {
            "CHEVRON": 3,
            "CAUTIONARY_WARNING_SIGNS": 1,
            "PROHIBITORY_MANDATORY_SIGNS": 1
        },
        "Median": {},
        "Center": {},
        "lat": 18.5943178,
        "lng": 84.21922225,
        "to_lat": 18.59067065,
        "to_lng": 84.21644843
    },
    "86085": {
        "Avenue": {
            "PROHIBITORY_MANDATORY_SIGNS": 1,
            "HAZARD": 1
        },
        "Median": {
            "PROHIBITORY_MANDATORY_SIGNS": 1
        },
        "Center": {},
        "lat": 18.59067065,
        "lng": 84.21644843,
        "to_lat": 18.58716933,
        "to_lng": 84.21340678
    },
    "86585": {
        "Avenue": {
            "CAUTIONARY_WARNING_SIGNS": 1
        },
        "Median": {},
        "Center": {},
        "lat": 18.58716933,
        "lng": 84.21340678,
        "to_lat": 18.58382143,
        "to_lng": 84.21041768
    },
    "87085": {
        "Avenue": {
            "CAUTIONARY_WARNING_SIGNS": 1
        },
        "Median": {
            "CAUTIONARY_WARNING_SIGNS": 1
        },
        "Center": {},
        "lat": 18.58382143,
        "lng": 84.21041768,
        "to_lat": 18.58037005,
        "to_lng": 84.20718237
    },
    "87585": {
        "Avenue": {
            "HAZARD": 1
        },
        "Median": {},
        "Center": {},
        "lat": 18.58037005,
        "lng": 84.20718237,
        "to_lat": 18.57708865,
        "to_lng": 84.20399423
    },
    "88085": {
        "Avenue": {
            "HAZARD": 2,
            "INFORMATORY_SIGNS": 2,
            "CAUTIONARY_WARNING_SIGNS": 1,
            "CHEVRON": 2
        },
        "Median": {},
        "Center": {},
        "lat": 18.57708865,
        "lng": 84.20399423,
        "to_lat": 18.57381728,
        "to_lng": 84.20074273
    },
    "88585": {
        "Avenue": {
            "INFORMATORY_SIGNS": 2,
            "PROHIBITORY_MANDATORY_SIGNS": 1,
            "HAZARD": 1
        },
        "Median": {
            "CAUTIONARY_WARNING_SIGNS": 1
        },
        "Center": {},
        "lat": 18.57381728,
        "lng": 84.20074273,
        "to_lat": 18.57120637,
        "to_lng": 84.19679288
    },
    "89085": {
        "Avenue": {
            "INFORMATORY_SIGNS": 3,
            "CAUTIONARY_WARNING_SIGNS": 1,
            "PROHIBITORY_MANDATORY_SIGNS": 2
        },
        "Median": {
            "HAZARD": 1
        },
        "Center": {},
        "lat": 18.57120637,
        "lng": 84.19679288,
        "to_lat": 18.56828727,
        "to_lng": 84.19320953
    },
    "89585": {
        "Avenue": {
            "HAZARD": 1
        },
        "Median": {
            "PROHIBITORY_MANDATORY_SIGNS": 1
        },
        "Center": {},
        "lat": 18.56828727,
        "lng": 84.19320953,
        "to_lat": 18.56519318,
        "to_lng": 84.18994933
    },
    "90085": {
        "Avenue": {
            "HAZARD": 1,
            "INFORMATORY_SIGNS": 1
        },
        "Median": {
            "PROHIBITORY_MANDATORY_SIGNS": 1,
            "CHEVRON": 2
        },
        "Center": {},
        "lat": 18.56519318,
        "lng": 84.18994933,
        "to_lat": 18.56196688,
        "to_lng": 84.18650527
    },
    "90585": {
        "Avenue": {
            "PROHIBITORY_MANDATORY_SIGNS": 1,
            "CAUTIONARY_WARNING_SIGNS": 1,
            "HAZARD": 1
        },
        "Median": {
            "CHEVRON": 4,
            "HAZARD": 1
        },
        "Center": {},
        "lat": 18.56196688,
        "lng": 84.18650527,
        "to_lat": 18.55843302,
        "to_lng": 84.183689
    },
    "91085": {
        "Avenue": {
            "INFORMATORY_SIGNS": 1,
            "CAUTIONARY_WARNING_SIGNS": 1,
            "PROHIBITORY_MANDATORY_SIGNS": 1
        },
        "Median": {},
        "Center": {},
        "lat": 18.55843302,
        "lng": 84.183689,
        "to_lat": 18.55473045,
        "to_lng": 84.1810065
    },
    "91585": {
        "Avenue": {
            "CAUTIONARY_WARNING_SIGNS": 1,
            "HAZARD": 1
        },
        "Median": {},
        "Center": {},
        "lat": 18.55473045,
        "lng": 84.1810065,
        "to_lat": 18.55121223,
        "to_lng": 84.17808188
    },
    "92085": {
        "Avenue": {
            "HAZARD": 3,
            "CAUTIONARY_WARNING_SIGNS": 1
        },
        "Median": {
            "CHEVRON": 1,
            "HAZARD": 1
        },
        "Center": {},
        "lat": 18.55121223,
        "lng": 84.17808188,
        "to_lat": 18.54707358,
        "to_lng": 84.17614077
    },
    "92585": {
        "Avenue": {},
        "Median": {
            "PROHIBITORY_MANDATORY_SIGNS": 1
        },
        "Center": {},
        "lat": 18.54707358,
        "lng": 84.17614077,
        "to_lat": 18.54290542,
        "to_lng": 84.17424333
    },
    "93085": {
        "Avenue": {
            "HAZARD": 2,
            "CHEVRON": 4
        },
        "Median": {
            "HAZARD": 1
        },
        "Center": {},
        "lat": 18.54290542,
        "lng": 84.17424333,
        "to_lat": 18.5391141,
        "to_lng": 84.17170342
    },
    "93585": {
        "Avenue": {
            "PROHIBITORY_MANDATORY_SIGNS": 1,
            "INFORMATORY_SIGNS": 1
        },
        "Median": {},
        "Center": {},
        "lat": 18.5391141,
        "lng": 84.17170342,
        "to_lat": 18.53625807,
        "to_lng": 84.16807507
    },
    "94085": {
        "Avenue": {
            "INFORMATORY_SIGNS": 1,
            "HAZARD": 1
        },
        "Median": {
            "CAUTIONARY_WARNING_SIGNS": 2,
            "INFORMATORY_SIGNS": 1,
            "HAZARD": 1,
            "PROHIBITORY_MANDATORY_SIGNS": 1
        },
        "Center": {},
        "lat": 18.53625807,
        "lng": 84.16807507,
        "to_lat": 18.53331412,
        "to_lng": 84.16442463
    },
    "94585": {
        "Avenue": {
            "INFORMATORY_SIGNS": 1,
            "CAUTIONARY_WARNING_SIGNS": 1,
            "PROHIBITORY_MANDATORY_SIGNS": 1,
            "HAZARD": 1
        },
        "Median": {},
        "Center": {},
        "lat": 18.53331412,
        "lng": 84.16442463,
        "to_lat": 18.53041882,
        "to_lng": 84.16085635
    },
    "95085": {
        "Avenue": {
            "HAZARD": 1,
            "INFORMATORY_SIGNS": 1
        },
        "Median": {
            "HAZARD": 1
        },
        "Center": {},
        "lat": 18.53041882,
        "lng": 84.16085635,
        "to_lat": 18.52740573,
        "to_lng": 84.15725667
    },
    "95585": {
        "Avenue": {
            "INFORMATORY_SIGNS": 3
        },
        "Median": {},
        "Center": {},
        "lat": 18.52740573,
        "lng": 84.15725667,
        "to_lat": 18.52452565,
        "to_lng": 84.15372053
    },
    "96085": {
        "Avenue": {
            "PROHIBITORY_MANDATORY_SIGNS": 2,
            "INFORMATORY_SIGNS": 1,
            "CAUTIONARY_WARNING_SIGNS": 1
        },
        "Median": {},
        "Center": {},
        "lat": 18.52452565,
        "lng": 84.15372053,
        "to_lat": 18.52161912,
        "to_lng": 84.1500161
    },
    "96585": {
        "Avenue": {
            "CAUTIONARY_WARNING_SIGNS": 1,
            "INFORMATORY_SIGNS": 2
        },
        "Median": {
            "CHEVRON": 3
        },
        "Center": {},
        "lat": 18.52161912,
        "lng": 84.1500161,
        "to_lat": 18.5187161,
        "to_lng": 84.14648577
    },
    "97085": {
        "Avenue": {
            "CAUTIONARY_WARNING_SIGNS": 1
        },
        "Median": {
            "CHEVRON": 1
        },
        "Center": {},
        "lat": 18.5187161,
        "lng": 84.14648577,
        "to_lat": 18.51507363,
        "to_lng": 84.14352273
    },
    "97585": {
        "Avenue": {
            "PROHIBITORY_MANDATORY_SIGNS": 1,
            "HAZARD": 2,
            "INFORMATORY_SIGNS": 1
        },
        "Median": {},
        "Center": {},
        "lat": 18.51507363,
        "lng": 84.14352273,
        "to_lat": 18.5115402,
        "to_lng": 84.1408151
    },
    "98085": {
        "Avenue": {
            "INFORMATORY_SIGNS": 1,
            "HAZARD": 2,
            "CAUTIONARY_WARNING_SIGNS": 1,
            "PROHIBITORY_MANDATORY_SIGNS": 1
        },
        "Median": {
            "HAZARD": 1
        },
        "Center": {},
        "lat": 18.5115402,
        "lng": 84.1408151,
        "to_lat": 18.50769542,
        "to_lng": 84.13830338
    },
    "98585": {
        "Avenue": {
            "INFORMATORY_SIGNS": 1,
            "HAZARD": 1,
            "PROHIBITORY_MANDATORY_SIGNS": 2
        },
        "Median": {},
        "Center": {},
        "lat": 18.50769542,
        "lng": 84.13830338,
        "to_lat": 18.50371257,
        "to_lng": 84.13596257
    },
    "99085": {
        "Avenue": {},
        "Median": {},
        "Center": {},
        "lat": 18.50371257,
        "lng": 84.13596257,
        "to_lat": 18.49974728,
        "to_lng": 84.1336836
    },
    "99585": {
        "Avenue": {
            "PROHIBITORY_MANDATORY_SIGNS": 1
        },
        "Median": {
            "CAUTIONARY_WARNING_SIGNS": 2,
            "PROHIBITORY_MANDATORY_SIGNS": 1
        },
        "Center": {},
        "lat": 18.49974728,
        "lng": 84.1336836,
        "to_lat": 18.4960629,
        "to_lng": 84.13102062
    },
    "100085": {
        "Avenue": {
            "INFORMATORY_SIGNS": 1,
            "HAZARD": 1
        },
        "Median": {},
        "Center": {},
        "lat": 18.4960629,
        "lng": 84.13102062,
        "to_lat": 18.49238403,
        "to_lng": 84.12855535
    },
    "100585": {
        "Avenue": {
            "CAUTIONARY_WARNING_SIGNS": 1,
            "HAZARD": 1
        },
        "Median": {},
        "Center": {},
        "lat": 18.49238403,
        "lng": 84.12855535,
        "to_lat": 18.48819345,
        "to_lng": 84.12629622
    },
    "101085": {
        "Avenue": {
            "HAZARD": 1,
            "CHEVRON": 3
        },
        "Median": {},
        "Center": {},
        "lat": 18.48819345,
        "lng": 84.12629622,
        "to_lat": 18.48414542,
        "to_lng": 84.1243705
    },
    "101585": {
        "Avenue": {
            "CHEVRON": 2,
            "INFORMATORY_SIGNS": 2,
            "HAZARD": 2,
            "CAUTIONARY_WARNING_SIGNS": 1
        },
        "Median": {},
        "Center": {},
        "lat": 18.48414542,
        "lng": 84.1243705,
        "to_lat": 18.4809254,
        "to_lng": 84.12100923
    },
    "102085": {
        "Avenue": {
            "HAZARD": 1,
            "PROHIBITORY_MANDATORY_SIGNS": 1,
            "CAUTIONARY_WARNING_SIGNS": 1,
            "INFORMATORY_SIGNS": 1
        },
        "Median": {
            "HAZARD": 1
        },
        "Center": {},
        "lat": 18.4809254,
        "lng": 84.12100923,
        "to_lat": 18.4779165,
        "to_lng": 84.11758625
    },
    "102585": {
        "Avenue": {
            "CAUTIONARY_WARNING_SIGNS": 1,
            "HAZARD": 2,
            "PROHIBITORY_MANDATORY_SIGNS": 2
        },
        "Median": {
            "HAZARD": 1
        },
        "Center": {},
        "lat": 18.4779165,
        "lng": 84.11758625,
        "to_lat": 18.47471905,
        "to_lng": 84.11424213
    },
    "103085": {
        "Avenue": {
            "PROHIBITORY_MANDATORY_SIGNS": 1,
            "CAUTIONARY_WARNING_SIGNS": 1
        },
        "Median": {},
        "Center": {},
        "lat": 18.47471905,
        "lng": 84.11424213,
        "to_lat": 18.47151725,
        "to_lng": 84.1108749
    },
    "103585": {
        "Avenue": {
            "CAUTIONARY_WARNING_SIGNS": 1,
            "HAZARD": 2,
            "INFORMATORY_SIGNS": 1
        },
        "Median": {},
        "Center": {},
        "lat": 18.47151725,
        "lng": 84.1108749,
        "to_lat": 18.4683051,
        "to_lng": 84.10747755
    },
    "104085": {
        "Avenue": {
            "INFORMATORY_SIGNS": 1
        },
        "Median": {},
        "Center": {},
        "lat": 18.4683051,
        "lng": 84.10747755,
        "to_lat": 18.46514568,
        "to_lng": 84.1041767
    },
    "104585": {
        "Avenue": {
            "CAUTIONARY_WARNING_SIGNS": 1,
            "PROHIBITORY_MANDATORY_SIGNS": 2,
            "HAZARD": 1
        },
        "Median": {
            "CHEVRON": 5
        },
        "Center": {},
        "lat": 18.46514568,
        "lng": 84.1041767,
        "to_lat": 18.46160008,
        "to_lng": 84.10134015
    },
    "105085": {
        "Avenue": {
            "CHEVRON": 3
        },
        "Median": {
            "CHEVRON": 5
        },
        "Center": {},
        "lat": 18.46160008,
        "lng": 84.10134015,
        "to_lat": 18.45796593,
        "to_lng": 84.09856478
    },
    "105585": {
        "Avenue": {
            "CHEVRON": 2,
            "PROHIBITORY_MANDATORY_SIGNS": 1,
            "HAZARD": 1,
            "INFORMATORY_SIGNS": 1
        },
        "Median": {
            "CAUTIONARY_WARNING_SIGNS": 2,
            "PROHIBITORY_MANDATORY_SIGNS": 1,
            "HAZARD": 1
        },
        "Center": {},
        "lat": 18.45796593,
        "lng": 84.09856478,
        "to_lat": 18.45470442,
        "to_lng": 84.09522407
    },
    "106085": {
        "Avenue": {
            "INFORMATORY_SIGNS": 1,
            "HAZARD": 2
        },
        "Median": {},
        "Center": {},
        "lat": 18.45470442,
        "lng": 84.09522407,
        "to_lat": 18.45174973,
        "to_lng": 84.09175087
    },
    "106585": {
        "Avenue": {
            "INFORMATORY_SIGNS": 1
        },
        "Median": {},
        "Center": {},
        "lat": 18.45174973,
        "lng": 84.09175087,
        "to_lat": 18.44867725,
        "to_lng": 84.08826103
    },
    "107085": {
        "Avenue": {},
        "Median": {},
        "Center": {},
        "lat": 18.44867725,
        "lng": 84.08826103,
        "to_lat": 18.44603778,
        "to_lng": 84.08449737
    },
    "107585": {
        "Avenue": {
            "HAZARD": 1
        },
        "Median": {},
        "Center": {},
        "lat": 18.44603778,
        "lng": 84.08449737,
        "to_lat": 18.4433206,
        "to_lng": 84.08061388
    },
    "108085": {
        "Avenue": {
            "INFORMATORY_SIGNS": 1,
            "CAUTIONARY_WARNING_SIGNS": 1
        },
        "Median": {
            "INFORMATORY_SIGNS": 1
        },
        "Center": {},
        "lat": 18.4433206,
        "lng": 84.08061388,
        "to_lat": 18.44065612,
        "to_lng": 84.07673778
    },
    "108585": {
        "Avenue": {
            "INFORMATORY_SIGNS": 3,
            "HAZARD": 1
        },
        "Median": {},
        "Center": {},
        "lat": 18.44065612,
        "lng": 84.07673778,
        "to_lat": 18.43804393,
        "to_lng": 84.07298118
    },
    "109085": {
        "Avenue": {},
        "Median": {
            "CAUTIONARY_WARNING_SIGNS": 2
        },
        "Center": {},
        "lat": 18.43804393,
        "lng": 84.07298118,
        "to_lat": 18.43548423,
        "to_lng": 84.06908082
    },
    "109585": {
        "Avenue": {},
        "Median": {
            "HAZARD": 1
        },
        "Center": {},
        "lat": 18.43548423,
        "lng": 84.06908082,
        "to_lat": 18.43321362,
        "to_lng": 84.0649806
    },
    "110085": {
        "Avenue": {
            "INFORMATORY_SIGNS": 4,
            "HAZARD": 1
        },
        "Median": {},
        "Center": {},
        "lat": 18.43321362,
        "lng": 84.0649806,
        "to_lat": 18.43063065,
        "to_lng": 84.06093757
    },
    "110585": {
        "Avenue": {
            "CAUTIONARY_WARNING_SIGNS": 1,
            "HAZARD": 1,
            "INFORMATORY_SIGNS": 1
        },
        "Median": {},
        "Center": {},
        "lat": 18.43063065,
        "lng": 84.06093757,
        "to_lat": 18.43029737,
        "to_lng": 84.06048107
    }
}