{
    "0": {
        "Left": {
            "INFORMATORY_SIGNS": 1
        },
        "Right": {},
        "lat": 15.597505,
        "lng": 78.17329667,
        "to_lat": 15.60039833,
        "to_lng": 78.17280167
    },
    "341": {
        "Left": {
            "HAZARD": 1,
            "INFORMATORY_SIGNS": 1
        },
        "Right": {},
        "lat": 15.60039833,
        "lng": 78.17280167,
        "to_lat": 15.60497167,
        "to_lng": 78.17270167
    },
    "841": {
        "Left": {},
        "Right": {},
        "lat": 15.60497167,
        "lng": 78.17270167,
        "to_lat": 15.60543667,
        "to_lng": 78.172665
    }
}